damnit/__init__.py
damnit/api.py
damnit/cli.py
damnit/context.py
damnit/definitions.py
damnit/migrations.py
damnit/util.py
damnit/backend/__init__.py
damnit/backend/db.py
damnit/backend/extract_data.py
damnit/backend/extraction_control.py
damnit/backend/listener.py
damnit/backend/supervisord.conf
damnit/backend/supervisord.py
damnit/backend/test_listener.py
damnit/backend/user_variables.py
damnit/ctx-templates/SA1_base.py
damnit/ctx-templates/SA2_base.py
damnit/ctx-templates/SA3_base.py
damnit/ctxsupport/README.md
damnit/ctxsupport/ctxrunner.py
damnit/ctxsupport/damnit_ctx.py
damnit/gui/__init__.py
damnit/gui/editor.py
damnit/gui/kafka.py
damnit/gui/main_window.py
damnit/gui/new_context_dialog.py
damnit/gui/new_context_dialog.ui
damnit/gui/new_context_dialog_ui.py
damnit/gui/open_dialog.py
damnit/gui/open_dialog.ui
damnit/gui/open_dialog_ui.py
damnit/gui/plot.py
damnit/gui/process.py
damnit/gui/standalone_comments.py
damnit/gui/table.py
damnit/gui/table_filter.py
damnit/gui/theme.py
damnit/gui/user_variables.py
damnit/gui/util.py
damnit/gui/web_viewer.py
damnit/gui/widgets.py
damnit/gui/zulip_messenger.py
damnit/gui/ico/AMORE.png
damnit/gui/ico/closed-hover.png
damnit/gui/ico/closed.png
damnit/gui/ico/export.png
damnit/gui/ico/green_circle.svg
damnit/gui/ico/lock_closed_icon.png
damnit/gui/ico/lock_open_icon.png
damnit/gui/ico/lock_opening_icon.png
damnit/gui/ico/open-hover.png
damnit/gui/ico/open.png
damnit/gui/ico/red_circle.svg
damnit/gui/ico/search_icon.png
damnit/gui/ico/wait_circle.svg
damnit/gui/ico/yellow_circle.svg
damnit-0.2.1.dist-info/entry_points.txt
damnit-0.2.1.dist-info/licenses/LICENSE
damnit-0.2.1.dist-info/WHEEL
damnit-0.2.1.dist-info/METADATA
damnit-0.2.1.dist-info/RECORD
